routerrific/__init__.py
routerrific/expr.py
routerrific/router.py
routerrific/guards/__init__.py
routerrific/guards/header.py
routerrific/guards/method.py
routerrific/guards/parameter.py
routerrific/guards/path.py
routerrific/guards/query.py
routerrific/guards/integrations/msgspec.py
routerrific/tests/__init__.py
routerrific/tests/test_dispatch.py
routerrific/tests/test_expr.py
routerrific/tests/test_matchers.py
django_routerrific-0.1.0.dist-info/LICENSE
django_routerrific-0.1.0.dist-info/WHEEL
django_routerrific-0.1.0.dist-info/METADATA
django_routerrific-0.1.0.dist-info/RECORD
